{
  "updated_at": "2025-12-28T14:35:37Z",
  "endpoint": "https://12mse3zde5.execute-api.ap-south-1.amazonaws.com/Prod/analytics",
  "region": "ap-south-1",
  "status": "DOWN",
  "http_code": 0,
  "latency_ms": 90,
  "history": [
    {
      "t": "2025-12-24T23:32:22Z",
      "code": 0,
      "lat": 38,
      "s": "DOWN"
    },
    {
      "t": "2025-12-24T23:49:31Z",
      "code": 0,
      "lat": 99,
      "s": "DOWN"
    },
    {
      "t": "2025-12-25T01:14:42Z",
      "code": 0,
      "lat": 85,
      "s": "DOWN"
    },
    {
      "t": "2025-12-25T03:03:15Z",
      "code": 0,
      "lat": 37,
      "s": "DOWN"
    },
    {
      "t": "2025-12-25T04:06:44Z",
      "code": 0,
      "lat": 53,
      "s": "DOWN"
    },
    {
      "t": "2025-12-25T04:49:29Z",
      "code": 0,
      "lat": 55,
      "s": "DOWN"
    },
    {
      "t": "2025-12-25T05:20:07Z",
      "code": 0,
      "lat": 62,
      "s": "DOWN"
    },
    {
      "t": "2025-12-25T05:45:48Z",
      "code": 0,
      "lat": 63,
      "s": "DOWN"
    },
    {
      "t": "2025-12-25T06:25:30Z",
      "code": 0,
      "lat": 30,
      "s": "DOWN"
    },
    {
      "t": "2025-12-25T06:54:00Z",
      "code": 0,
      "lat": 76,
      "s": "DOWN"
    },
    {
      "t": "2025-12-25T07:18:26Z",
      "code": 0,
      "lat": 36,
      "s": "DOWN"
    },
    {
      "t": "2025-12-25T07:40:24Z",
      "code": 0,
      "lat": 69,
      "s": "DOWN"
    },
    {
      "t": "2025-12-25T07:49:46Z",
      "code": 0,
      "lat": 58,
      "s": "DOWN"
    },
    {
      "t": "2025-12-25T08:21:51Z",
      "code": 0,
      "lat": 41,
      "s": "DOWN"
    },
    {
      "t": "2025-12-25T08:49:20Z",
      "code": 0,
      "lat": 16,
      "s": "DOWN"
    },
    {
      "t": "2025-12-25T09:18:35Z",
      "code": 0,
      "lat": 123,
      "s": "DOWN"
    },
    {
      "t": "2025-12-25T09:42:58Z",
      "code": 0,
      "lat": 24,
      "s": "DOWN"
    },
    {
      "t": "2025-12-25T09:52:52Z",
      "code": 0,
      "lat": 87,
      "s": "DOWN"
    },
    {
      "t": "2025-12-25T10:17:11Z",
      "code": 0,
      "lat": 72,
      "s": "DOWN"
    },
    {
      "t": "2025-12-25T10:44:16Z",
      "code": 0,
      "lat": 145,
      "s": "DOWN"
    },
    {
      "t": "2025-12-25T10:54:16Z",
      "code": 0,
      "lat": 35,
      "s": "DOWN"
    },
    {
      "t": "2025-12-25T11:14:01Z",
      "code": 0,
      "lat": 117,
      "s": "DOWN"
    },
    {
      "t": "2025-12-25T11:30:22Z",
      "code": 0,
      "lat": 70,
      "s": "DOWN"
    },
    {
      "t": "2025-12-25T11:48:29Z",
      "code": 0,
      "lat": 67,
      "s": "DOWN"
    },
    {
      "t": "2025-12-25T12:31:50Z",
      "code": 0,
      "lat": 23,
      "s": "DOWN"
    },
    {
      "t": "2025-12-25T13:20:29Z",
      "code": 0,
      "lat": 64,
      "s": "DOWN"
    },
    {
      "t": "2025-12-25T13:47:52Z",
      "code": 0,
      "lat": 111,
      "s": "DOWN"
    },
    {
      "t": "2025-12-25T14:15:17Z",
      "code": 0,
      "lat": 89,
      "s": "DOWN"
    },
    {
      "t": "2025-12-25T14:37:28Z",
      "code": 0,
      "lat": 57,
      "s": "DOWN"
    },
    {
      "t": "2025-12-25T14:52:03Z",
      "code": 0,
      "lat": 35,
      "s": "DOWN"
    },
    {
      "t": "2025-12-25T15:15:40Z",
      "code": 0,
      "lat": 124,
      "s": "DOWN"
    },
    {
      "t": "2025-12-25T15:40:39Z",
      "code": 0,
      "lat": 65,
      "s": "DOWN"
    },
    {
      "t": "2025-12-25T15:50:36Z",
      "code": 0,
      "lat": 149,
      "s": "DOWN"
    },
    {
      "t": "2025-12-25T16:19:29Z",
      "code": 0,
      "lat": 64,
      "s": "DOWN"
    },
    {
      "t": "2025-12-25T16:47:16Z",
      "code": 0,
      "lat": 44,
      "s": "DOWN"
    },
    {
      "t": "2025-12-25T17:14:11Z",
      "code": 0,
      "lat": 26,
      "s": "DOWN"
    },
    {
      "t": "2025-12-25T17:33:12Z",
      "code": 0,
      "lat": 27,
      "s": "DOWN"
    },
    {
      "t": "2025-12-25T17:49:37Z",
      "code": 0,
      "lat": 60,
      "s": "DOWN"
    },
    {
      "t": "2025-12-25T18:22:40Z",
      "code": 0,
      "lat": 136,
      "s": "DOWN"
    },
    {
      "t": "2025-12-25T18:50:09Z",
      "code": 0,
      "lat": 65,
      "s": "DOWN"
    },
    {
      "t": "2025-12-25T19:12:39Z",
      "code": 0,
      "lat": 89,
      "s": "DOWN"
    },
    {
      "t": "2025-12-25T19:27:32Z",
      "code": 0,
      "lat": 35,
      "s": "DOWN"
    },
    {
      "t": "2025-12-25T19:38:17Z",
      "code": 0,
      "lat": 85,
      "s": "DOWN"
    },
    {
      "t": "2025-12-25T19:49:00Z",
      "code": 0,
      "lat": 141,
      "s": "DOWN"
    },
    {
      "t": "2025-12-25T20:17:40Z",
      "code": 0,
      "lat": 32,
      "s": "DOWN"
    },
    {
      "t": "2025-12-25T20:42:13Z",
      "code": 0,
      "lat": 24,
      "s": "DOWN"
    },
    {
      "t": "2025-12-25T20:53:03Z",
      "code": 0,
      "lat": 135,
      "s": "DOWN"
    },
    {
      "t": "2025-12-25T21:14:19Z",
      "code": 0,
      "lat": 100,
      "s": "DOWN"
    },
    {
      "t": "2025-12-25T21:31:39Z",
      "code": 0,
      "lat": 48,
      "s": "DOWN"
    },
    {
      "t": "2025-12-25T21:49:10Z",
      "code": 0,
      "lat": 31,
      "s": "DOWN"
    },
    {
      "t": "2025-12-25T22:15:22Z",
      "code": 0,
      "lat": 60,
      "s": "DOWN"
    },
    {
      "t": "2025-12-25T22:37:03Z",
      "code": 0,
      "lat": 93,
      "s": "DOWN"
    },
    {
      "t": "2025-12-25T22:51:30Z",
      "code": 0,
      "lat": 55,
      "s": "DOWN"
    },
    {
      "t": "2025-12-25T23:15:20Z",
      "code": 0,
      "lat": 62,
      "s": "DOWN"
    },
    {
      "t": "2025-12-25T23:38:46Z",
      "code": 0,
      "lat": 63,
      "s": "DOWN"
    },
    {
      "t": "2025-12-25T23:49:51Z",
      "code": 0,
      "lat": 38,
      "s": "DOWN"
    },
    {
      "t": "2025-12-26T01:15:06Z",
      "code": 0,
      "lat": 85,
      "s": "DOWN"
    },
    {
      "t": "2025-12-26T03:01:13Z",
      "code": 0,
      "lat": 91,
      "s": "DOWN"
    },
    {
      "t": "2025-12-26T04:03:51Z",
      "code": 0,
      "lat": 68,
      "s": "DOWN"
    },
    {
      "t": "2025-12-26T04:47:18Z",
      "code": 0,
      "lat": 104,
      "s": "DOWN"
    },
    {
      "t": "2025-12-26T05:17:49Z",
      "code": 0,
      "lat": 32,
      "s": "DOWN"
    },
    {
      "t": "2025-12-26T05:44:04Z",
      "code": 0,
      "lat": 60,
      "s": "DOWN"
    },
    {
      "t": "2025-12-26T05:53:48Z",
      "code": 0,
      "lat": 38,
      "s": "DOWN"
    },
    {
      "t": "2025-12-26T06:25:06Z",
      "code": 0,
      "lat": 32,
      "s": "DOWN"
    },
    {
      "t": "2025-12-26T06:53:43Z",
      "code": 0,
      "lat": 86,
      "s": "DOWN"
    },
    {
      "t": "2025-12-26T07:17:56Z",
      "code": 0,
      "lat": 34,
      "s": "DOWN"
    },
    {
      "t": "2025-12-26T07:40:45Z",
      "code": 0,
      "lat": 31,
      "s": "DOWN"
    },
    {
      "t": "2025-12-26T07:50:19Z",
      "code": 0,
      "lat": 113,
      "s": "DOWN"
    },
    {
      "t": "2025-12-26T08:21:27Z",
      "code": 0,
      "lat": 61,
      "s": "DOWN"
    },
    {
      "t": "2025-12-26T08:48:55Z",
      "code": 0,
      "lat": 38,
      "s": "DOWN"
    },
    {
      "t": "2025-12-26T09:18:17Z",
      "code": 0,
      "lat": 161,
      "s": "DOWN"
    },
    {
      "t": "2025-12-26T09:42:33Z",
      "code": 0,
      "lat": 41,
      "s": "DOWN"
    },
    {
      "t": "2025-12-26T09:52:14Z",
      "code": 0,
      "lat": 117,
      "s": "DOWN"
    },
    {
      "t": "2025-12-26T10:17:01Z",
      "code": 0,
      "lat": 139,
      "s": "DOWN"
    },
    {
      "t": "2025-12-26T10:44:21Z",
      "code": 0,
      "lat": 110,
      "s": "DOWN"
    },
    {
      "t": "2025-12-26T10:54:23Z",
      "code": 0,
      "lat": 25,
      "s": "DOWN"
    },
    {
      "t": "2025-12-26T11:14:29Z",
      "code": 0,
      "lat": 23,
      "s": "DOWN"
    },
    {
      "t": "2025-12-26T11:30:52Z",
      "code": 0,
      "lat": 88,
      "s": "DOWN"
    },
    {
      "t": "2025-12-26T11:48:59Z",
      "code": 0,
      "lat": 84,
      "s": "DOWN"
    },
    {
      "t": "2025-12-26T12:31:46Z",
      "code": 0,
      "lat": 87,
      "s": "DOWN"
    },
    {
      "t": "2025-12-26T13:20:44Z",
      "code": 0,
      "lat": 76,
      "s": "DOWN"
    },
    {
      "t": "2025-12-26T13:48:39Z",
      "code": 0,
      "lat": 85,
      "s": "DOWN"
    },
    {
      "t": "2025-12-26T14:15:51Z",
      "code": 0,
      "lat": 23,
      "s": "DOWN"
    },
    {
      "t": "2025-12-26T14:43:06Z",
      "code": 0,
      "lat": 56,
      "s": "DOWN"
    },
    {
      "t": "2025-12-26T14:53:31Z",
      "code": 0,
      "lat": 89,
      "s": "DOWN"
    },
    {
      "t": "2025-12-26T15:16:06Z",
      "code": 0,
      "lat": 41,
      "s": "DOWN"
    },
    {
      "t": "2025-12-26T15:41:01Z",
      "code": 0,
      "lat": 118,
      "s": "DOWN"
    },
    {
      "t": "2025-12-26T15:51:18Z",
      "code": 0,
      "lat": 43,
      "s": "DOWN"
    },
    {
      "t": "2025-12-26T16:18:17Z",
      "code": 0,
      "lat": 23,
      "s": "DOWN"
    },
    {
      "t": "2025-12-26T16:45:09Z",
      "code": 0,
      "lat": 27,
      "s": "DOWN"
    },
    {
      "t": "2025-12-26T16:56:43Z",
      "code": 0,
      "lat": 62,
      "s": "DOWN"
    },
    {
      "t": "2025-12-26T17:16:14Z",
      "code": 0,
      "lat": 105,
      "s": "DOWN"
    },
    {
      "t": "2025-12-26T17:39:09Z",
      "code": 0,
      "lat": 98,
      "s": "DOWN"
    },
    {
      "t": "2025-12-26T17:49:14Z",
      "code": 0,
      "lat": 24,
      "s": "DOWN"
    },
    {
      "t": "2025-12-26T18:22:46Z",
      "code": 0,
      "lat": 22,
      "s": "DOWN"
    },
    {
      "t": "2025-12-26T18:49:57Z",
      "code": 0,
      "lat": 59,
      "s": "DOWN"
    },
    {
      "t": "2025-12-26T19:12:36Z",
      "code": 0,
      "lat": 47,
      "s": "DOWN"
    },
    {
      "t": "2025-12-26T19:27:13Z",
      "code": 0,
      "lat": 50,
      "s": "DOWN"
    },
    {
      "t": "2025-12-26T19:38:15Z",
      "code": 0,
      "lat": 136,
      "s": "DOWN"
    },
    {
      "t": "2025-12-26T19:48:55Z",
      "code": 0,
      "lat": 87,
      "s": "DOWN"
    },
    {
      "t": "2025-12-26T20:16:45Z",
      "code": 0,
      "lat": 56,
      "s": "DOWN"
    },
    {
      "t": "2025-12-26T20:41:06Z",
      "code": 0,
      "lat": 38,
      "s": "DOWN"
    },
    {
      "t": "2025-12-26T20:51:38Z",
      "code": 0,
      "lat": 90,
      "s": "DOWN"
    },
    {
      "t": "2025-12-26T21:13:44Z",
      "code": 0,
      "lat": 88,
      "s": "DOWN"
    },
    {
      "t": "2025-12-26T21:30:38Z",
      "code": 0,
      "lat": 119,
      "s": "DOWN"
    },
    {
      "t": "2025-12-26T21:48:57Z",
      "code": 0,
      "lat": 41,
      "s": "DOWN"
    },
    {
      "t": "2025-12-26T22:15:30Z",
      "code": 0,
      "lat": 60,
      "s": "DOWN"
    },
    {
      "t": "2025-12-26T22:42:02Z",
      "code": 0,
      "lat": 23,
      "s": "DOWN"
    },
    {
      "t": "2025-12-26T22:52:02Z",
      "code": 0,
      "lat": 105,
      "s": "DOWN"
    },
    {
      "t": "2025-12-26T23:15:23Z",
      "code": 0,
      "lat": 92,
      "s": "DOWN"
    },
    {
      "t": "2025-12-26T23:38:46Z",
      "code": 0,
      "lat": 40,
      "s": "DOWN"
    },
    {
      "t": "2025-12-26T23:49:40Z",
      "code": 0,
      "lat": 126,
      "s": "DOWN"
    },
    {
      "t": "2025-12-27T01:13:13Z",
      "code": 0,
      "lat": 67,
      "s": "DOWN"
    },
    {
      "t": "2025-12-27T02:58:30Z",
      "code": 0,
      "lat": 69,
      "s": "DOWN"
    },
    {
      "t": "2025-12-27T03:56:20Z",
      "code": 0,
      "lat": 87,
      "s": "DOWN"
    },
    {
      "t": "2025-12-27T04:30:30Z",
      "code": 0,
      "lat": 111,
      "s": "DOWN"
    },
    {
      "t": "2025-12-27T04:57:08Z",
      "code": 0,
      "lat": 56,
      "s": "DOWN"
    },
    {
      "t": "2025-12-27T05:20:58Z",
      "code": 0,
      "lat": 34,
      "s": "DOWN"
    },
    {
      "t": "2025-12-27T05:43:44Z",
      "code": 0,
      "lat": 63,
      "s": "DOWN"
    },
    {
      "t": "2025-12-27T05:53:39Z",
      "code": 0,
      "lat": 31,
      "s": "DOWN"
    },
    {
      "t": "2025-12-27T06:23:32Z",
      "code": 0,
      "lat": 114,
      "s": "DOWN"
    },
    {
      "t": "2025-12-27T06:51:48Z",
      "code": 0,
      "lat": 25,
      "s": "DOWN"
    },
    {
      "t": "2025-12-27T07:15:19Z",
      "code": 0,
      "lat": 84,
      "s": "DOWN"
    },
    {
      "t": "2025-12-27T07:32:06Z",
      "code": 0,
      "lat": 51,
      "s": "DOWN"
    },
    {
      "t": "2025-12-27T07:48:57Z",
      "code": 0,
      "lat": 16,
      "s": "DOWN"
    },
    {
      "t": "2025-12-27T08:20:12Z",
      "code": 0,
      "lat": 65,
      "s": "DOWN"
    },
    {
      "t": "2025-12-27T08:46:59Z",
      "code": 0,
      "lat": 48,
      "s": "DOWN"
    },
    {
      "t": "2025-12-27T09:15:38Z",
      "code": 0,
      "lat": 74,
      "s": "DOWN"
    },
    {
      "t": "2025-12-27T09:39:41Z",
      "code": 0,
      "lat": 39,
      "s": "DOWN"
    },
    {
      "t": "2025-12-27T09:49:07Z",
      "code": 0,
      "lat": 49,
      "s": "DOWN"
    },
    {
      "t": "2025-12-27T10:15:17Z",
      "code": 0,
      "lat": 132,
      "s": "DOWN"
    },
    {
      "t": "2025-12-27T10:42:24Z",
      "code": 0,
      "lat": 149,
      "s": "DOWN"
    },
    {
      "t": "2025-12-27T10:51:57Z",
      "code": 0,
      "lat": 32,
      "s": "DOWN"
    },
    {
      "t": "2025-12-27T11:12:29Z",
      "code": 0,
      "lat": 14,
      "s": "DOWN"
    },
    {
      "t": "2025-12-27T11:27:43Z",
      "code": 0,
      "lat": 43,
      "s": "DOWN"
    },
    {
      "t": "2025-12-27T11:38:32Z",
      "code": 0,
      "lat": 64,
      "s": "DOWN"
    },
    {
      "t": "2025-12-27T11:48:56Z",
      "code": 0,
      "lat": 109,
      "s": "DOWN"
    },
    {
      "t": "2025-12-27T12:29:39Z",
      "code": 0,
      "lat": 50,
      "s": "DOWN"
    },
    {
      "t": "2025-12-27T13:06:57Z",
      "code": 0,
      "lat": 77,
      "s": "DOWN"
    },
    {
      "t": "2025-12-27T13:38:56Z",
      "code": 0,
      "lat": 46,
      "s": "DOWN"
    },
    {
      "t": "2025-12-27T13:50:48Z",
      "code": 0,
      "lat": 64,
      "s": "DOWN"
    },
    {
      "t": "2025-12-27T14:14:01Z",
      "code": 0,
      "lat": 93,
      "s": "DOWN"
    },
    {
      "t": "2025-12-27T14:34:00Z",
      "code": 0,
      "lat": 80,
      "s": "DOWN"
    },
    {
      "t": "2025-12-27T14:49:39Z",
      "code": 0,
      "lat": 66,
      "s": "DOWN"
    },
    {
      "t": "2025-12-27T15:14:48Z",
      "code": 0,
      "lat": 40,
      "s": "DOWN"
    },
    {
      "t": "2025-12-27T15:32:40Z",
      "code": 0,
      "lat": 19,
      "s": "DOWN"
    },
    {
      "t": "2025-12-27T15:49:12Z",
      "code": 0,
      "lat": 23,
      "s": "DOWN"
    },
    {
      "t": "2025-12-27T16:18:34Z",
      "code": 0,
      "lat": 66,
      "s": "DOWN"
    },
    {
      "t": "2025-12-27T16:45:08Z",
      "code": 0,
      "lat": 119,
      "s": "DOWN"
    },
    {
      "t": "2025-12-27T16:56:05Z",
      "code": 0,
      "lat": 110,
      "s": "DOWN"
    },
    {
      "t": "2025-12-27T17:15:03Z",
      "code": 0,
      "lat": 17,
      "s": "DOWN"
    },
    {
      "t": "2025-12-27T17:32:33Z",
      "code": 0,
      "lat": 140,
      "s": "DOWN"
    },
    {
      "t": "2025-12-27T17:49:00Z",
      "code": 0,
      "lat": 100,
      "s": "DOWN"
    },
    {
      "t": "2025-12-27T18:21:39Z",
      "code": 0,
      "lat": 37,
      "s": "DOWN"
    },
    {
      "t": "2025-12-27T18:48:48Z",
      "code": 0,
      "lat": 23,
      "s": "DOWN"
    },
    {
      "t": "2025-12-27T19:11:50Z",
      "code": 0,
      "lat": 106,
      "s": "DOWN"
    },
    {
      "t": "2025-12-27T19:26:21Z",
      "code": 0,
      "lat": 39,
      "s": "DOWN"
    },
    {
      "t": "2025-12-27T19:36:28Z",
      "code": 0,
      "lat": 25,
      "s": "DOWN"
    },
    {
      "t": "2025-12-27T19:48:58Z",
      "code": 0,
      "lat": 29,
      "s": "DOWN"
    },
    {
      "t": "2025-12-27T20:16:48Z",
      "code": 0,
      "lat": 43,
      "s": "DOWN"
    },
    {
      "t": "2025-12-27T20:41:35Z",
      "code": 0,
      "lat": 88,
      "s": "DOWN"
    },
    {
      "t": "2025-12-27T20:51:29Z",
      "code": 0,
      "lat": 75,
      "s": "DOWN"
    },
    {
      "t": "2025-12-27T21:13:39Z",
      "code": 0,
      "lat": 58,
      "s": "DOWN"
    },
    {
      "t": "2025-12-27T21:30:24Z",
      "code": 0,
      "lat": 67,
      "s": "DOWN"
    },
    {
      "t": "2025-12-27T21:48:43Z",
      "code": 0,
      "lat": 25,
      "s": "DOWN"
    },
    {
      "t": "2025-12-27T22:14:59Z",
      "code": 0,
      "lat": 81,
      "s": "DOWN"
    },
    {
      "t": "2025-12-27T22:35:36Z",
      "code": 0,
      "lat": 118,
      "s": "DOWN"
    },
    {
      "t": "2025-12-27T22:50:20Z",
      "code": 0,
      "lat": 29,
      "s": "DOWN"
    },
    {
      "t": "2025-12-27T23:14:27Z",
      "code": 0,
      "lat": 41,
      "s": "DOWN"
    },
    {
      "t": "2025-12-27T23:32:00Z",
      "code": 0,
      "lat": 60,
      "s": "DOWN"
    },
    {
      "t": "2025-12-27T23:49:08Z",
      "code": 0,
      "lat": 74,
      "s": "DOWN"
    },
    {
      "t": "2025-12-28T01:23:17Z",
      "code": 0,
      "lat": 90,
      "s": "DOWN"
    },
    {
      "t": "2025-12-28T03:20:53Z",
      "code": 0,
      "lat": 807,
      "s": "DOWN"
    },
    {
      "t": "2025-12-28T04:29:36Z",
      "code": 0,
      "lat": 65,
      "s": "DOWN"
    },
    {
      "t": "2025-12-28T05:00:18Z",
      "code": 0,
      "lat": 99,
      "s": "DOWN"
    },
    {
      "t": "2025-12-28T05:38:47Z",
      "code": 0,
      "lat": 99,
      "s": "DOWN"
    },
    {
      "t": "2025-12-28T05:53:34Z",
      "code": 0,
      "lat": 132,
      "s": "DOWN"
    },
    {
      "t": "2025-12-28T06:24:13Z",
      "code": 0,
      "lat": 116,
      "s": "DOWN"
    },
    {
      "t": "2025-12-28T06:52:04Z",
      "code": 0,
      "lat": 44,
      "s": "DOWN"
    },
    {
      "t": "2025-12-28T07:16:12Z",
      "code": 0,
      "lat": 68,
      "s": "DOWN"
    },
    {
      "t": "2025-12-28T07:39:09Z",
      "code": 0,
      "lat": 31,
      "s": "DOWN"
    },
    {
      "t": "2025-12-28T07:49:09Z",
      "code": 0,
      "lat": 37,
      "s": "DOWN"
    },
    {
      "t": "2025-12-28T08:20:30Z",
      "code": 0,
      "lat": 109,
      "s": "DOWN"
    },
    {
      "t": "2025-12-28T08:47:08Z",
      "code": 0,
      "lat": 57,
      "s": "DOWN"
    },
    {
      "t": "2025-12-28T09:15:33Z",
      "code": 0,
      "lat": 87,
      "s": "DOWN"
    },
    {
      "t": "2025-12-28T09:39:55Z",
      "code": 0,
      "lat": 20,
      "s": "DOWN"
    },
    {
      "t": "2025-12-28T09:49:27Z",
      "code": 0,
      "lat": 88,
      "s": "DOWN"
    },
    {
      "t": "2025-12-28T10:15:31Z",
      "code": 0,
      "lat": 84,
      "s": "DOWN"
    },
    {
      "t": "2025-12-28T10:43:00Z",
      "code": 0,
      "lat": 90,
      "s": "DOWN"
    },
    {
      "t": "2025-12-28T10:52:41Z",
      "code": 0,
      "lat": 65,
      "s": "DOWN"
    },
    {
      "t": "2025-12-28T11:13:11Z",
      "code": 0,
      "lat": 60,
      "s": "DOWN"
    },
    {
      "t": "2025-12-28T11:28:46Z",
      "code": 0,
      "lat": 16,
      "s": "DOWN"
    },
    {
      "t": "2025-12-28T11:40:25Z",
      "code": 0,
      "lat": 98,
      "s": "DOWN"
    },
    {
      "t": "2025-12-28T11:48:49Z",
      "code": 0,
      "lat": 26,
      "s": "DOWN"
    },
    {
      "t": "2025-12-28T12:30:36Z",
      "code": 0,
      "lat": 60,
      "s": "DOWN"
    },
    {
      "t": "2025-12-28T13:17:55Z",
      "code": 0,
      "lat": 78,
      "s": "DOWN"
    },
    {
      "t": "2025-12-28T13:45:01Z",
      "code": 0,
      "lat": 93,
      "s": "DOWN"
    },
    {
      "t": "2025-12-28T13:54:35Z",
      "code": 0,
      "lat": 31,
      "s": "DOWN"
    },
    {
      "t": "2025-12-28T14:14:31Z",
      "code": 0,
      "lat": 39,
      "s": "DOWN"
    },
    {
      "t": "2025-12-28T14:35:37Z",
      "code": 0,
      "lat": 90,
      "s": "DOWN"
    }
  ]
}
